{
  "language": "zh-Hans",
  "timestamp": "2026-07-11T16:37:26.459662+00:00",
  "aggregatorSites": 39,
  "queryCount": 560,
  "totalUrls": 1105,
  "uniqueDomains": 455,
  "validatedCount": 35,
  "validationRemovedCount": 420,
  "newDomains": [
    "51manga.com",
    "ai-manga-generator.vercel.app",
    "anibk.com",
    "anime-gensaku-guide.onrender.com",
    "bomtoon.tw",
    "bookmanta.com",
    "comic-ogyaaa.com",
    "comic-walker.com",
    "comicbunch-kai.com",
    "corocoro.jp",
    "creative-comic.tw",
    "dm5.com",
    "dokumanhk.net",
    "exview.vercel.app",
    "fleur-collections.com",
    "gugu3.com",
    "hemh.cc",
    "hp-gamma-eight.vercel.app",
    "jump-mangasho.com",
    "manga-mee.jp",
    "manga-shinchan.com",
    "mangashare.vercel.app",
    "manhuaren.com",
    "mechacomic.jp",
    "mojoin.com",
    "mycomic.com",
    "nickstember.com",
    "piccoma.com",
    "pixiv-viewer.vercel.app",
    "quire-comic.com",
    "rit.vercel.app",
    "sg.vercel.app",
    "shonenmagazine.com",
    "to-corona-ex.com",
    "toptoon.net"
  ],
  "newDomainsDetail": [
    {
      "domain": "51manga.com",
      "matchedKeyword": "漫"
    },
    {
      "domain": "ai-manga-generator.vercel.app",
      "matchedKeyword": "漫"
    },
    {
      "domain": "anibk.com",
      "matchedKeyword": "漫"
    },
    {
      "domain": "anime-gensaku-guide.onrender.com",
      "matchedKeyword": "漫"
    },
    {
      "domain": "bomtoon.tw",
      "matchedKeyword": "漫"
    },
    {
      "domain": "bookmanta.com",
      "matchedKeyword": "漫"
    },
    {
      "domain": "comic-ogyaaa.com",
      "matchedKeyword": "漫"
    },
    {
      "domain": "comic-walker.com",
      "matchedKeyword": "漫"
    },
    {
      "domain": "comicbunch-kai.com",
      "matchedKeyword": "漫"
    },
    {
      "domain": "corocoro.jp",
      "matchedKeyword": "漫"
    },
    {
      "domain": "creative-comic.tw",
      "matchedKeyword": "漫"
    },
    {
      "domain": "dm5.com",
      "matchedKeyword": "漫"
    },
    {
      "domain": "dokumanhk.net",
      "matchedKeyword": "漫"
    },
    {
      "domain": "exview.vercel.app",
      "matchedKeyword": "漫"
    },
    {
      "domain": "fleur-collections.com",
      "matchedKeyword": "漫"
    },
    {
      "domain": "gugu3.com",
      "matchedKeyword": "漫"
    },
    {
      "domain": "hemh.cc",
      "matchedKeyword": "漫"
    },
    {
      "domain": "hp-gamma-eight.vercel.app",
      "matchedKeyword": "漫"
    },
    {
      "domain": "jump-mangasho.com",
      "matchedKeyword": "漫"
    },
    {
      "domain": "manga-mee.jp",
      "matchedKeyword": "漫"
    },
    {
      "domain": "manga-shinchan.com",
      "matchedKeyword": "漫"
    },
    {
      "domain": "mangashare.vercel.app",
      "matchedKeyword": "漫"
    },
    {
      "domain": "manhuaren.com",
      "matchedKeyword": "漫"
    },
    {
      "domain": "mechacomic.jp",
      "matchedKeyword": "漫"
    },
    {
      "domain": "mojoin.com",
      "matchedKeyword": "漫"
    },
    {
      "domain": "mycomic.com",
      "matchedKeyword": "漫"
    },
    {
      "domain": "nickstember.com",
      "matchedKeyword": "漫"
    },
    {
      "domain": "piccoma.com",
      "matchedKeyword": "漫"
    },
    {
      "domain": "pixiv-viewer.vercel.app",
      "matchedKeyword": "漫"
    },
    {
      "domain": "quire-comic.com",
      "matchedKeyword": "漫"
    },
    {
      "domain": "rit.vercel.app",
      "matchedKeyword": "漫"
    },
    {
      "domain": "sg.vercel.app",
      "matchedKeyword": "漫"
    },
    {
      "domain": "shonenmagazine.com",
      "matchedKeyword": "漫"
    },
    {
      "domain": "to-corona-ex.com",
      "matchedKeyword": "漫"
    },
    {
      "domain": "toptoon.net",
      "matchedKeyword": "漫"
    }
  ],
  "existingDomainCount": 35,
  "antiPatternByKeyword": {
    "18+": [
      "36kr.com",
      "bungatiga.onrender.com",
      "gov.tw",
      "mangacopy.com",
      "manhuascan.my",
      "mgread.io",
      "zamgot-dev.fly.dev",
      "zamgot-studio-dev.fly.dev"
    ],
    "18r": [
      "baidu.com",
      "docs.replit.com",
      "letschuhai.com",
      "nypl.org"
    ],
    "成人": [
      "d1hl9setcycg81.cloudfront.net",
      "d1na3f9tshcp4p.cloudfront.net",
      "d3ra9nqn08kl2e.cloudfront.net",
      "dnjtwtgi48217.cloudfront.net",
      "kuaikanmanhua.com",
      "vocus.cc"
    ]
  },
  "cleanedByKeyword": {
    "购物": [
      "gznf.net",
      "taobao.com",
      "tiktok.com"
    ],
    "教育": [
      "art-mate.net",
      "comicpash.jp",
      "ctext.org",
      "dongmanmanhua.cn",
      "ichefpos.com",
      "m21.hk",
      "office.com",
      "wenweipo.com"
    ],
    "基金": [
      "hkwl.org",
      "twreporter.org",
      "un.org"
    ],
    "直播": [
      "233dongman.com",
      "anifun.cn",
      "doc-openvideo.vercel.app",
      "dpz3pzoteix4e.cloudfront.net",
      "junyiacademy.org",
      "kilamanbo.world",
      "ofiii.com",
      "rthk.hk",
      "tkww.hk"
    ],
    "金融": [
      "d-dmm.com",
      "kalamanhua.com",
      "lmanhua.com",
      "manhuatuan.com",
      "taicca.tw"
    ],
    "房产": [
      "bilibili.com",
      "sina.cn",
      "sohu.com"
    ],
    "政府": [
      "cm3721.com",
      "comicavenue.hk",
      "hkcna.hk",
      "news.cn",
      "nthulabook.onrender.com",
      "ocacnews.net",
      "orangenews.hk",
      "qq.com",
      "taiwanngo.tw",
      "xinhuanet.com"
    ],
    "留学": [
      "haoduoman.com"
    ],
    "体育": [
      "anibase.net",
      "bzmanga.com",
      "d31a8rdj19i5e2.cloudfront.net",
      "d3aoa10o0410wd.cloudfront.net",
      "d6lvl8l2l26yp.cloudfront.net",
      "discsmijr8t6l.cloudfront.net",
      "manhuagui.com",
      "weimh.com"
    ],
    "法律": [
      "tcb.tw",
      "zhihu.com"
    ],
    "汽车": [
      "jiemian.com",
      "xiangchuifeng-github-io.vercel.app",
      "yfsp.tv"
    ],
    "电影": [
      "douban.com",
      "xiehuio.com",
      "yinghuaanime.com"
    ],
    "旅游": [
      "iqiyi.com"
    ],
    "编程": [
      "163.com",
      "axutongxue.onrender.com",
      "v2ex.vercel.app"
    ],
    "导航": [
      "blog-ffzz.vercel.app",
      "qianchuan.onrender.com",
      "sadg166.pages.dev",
      "ubereats.com",
      "unblockthetruth.onrender.com",
      "wooey.fly.dev"
    ],
    "医疗": [
      "linkedin.com"
    ],
    "软件": [
      "fvtt-cn.vercel.app"
    ],
    "博客": [
      "dongjian.vercel.app"
    ]
  },
  "allDiscoveredDomains": [
    "10086.cn",
    "163.com",
    "17173.com",
    "21jingji.com",
    "233dongman.com",
    "2k.com",
    "36kr.com",
    "51manga.com",
    "ac.jp",
    "addon-marvel.onrender.com",
    "ai-manga-generator.vercel.app",
    "aihr.com",
    "amazon.com",
    "anhuinews.com",
    "anibase.net",
    "anibk.com",
    "anibrain-closure.pages.dev",
    "anifun.cn",
    "anime-gensaku-guide.onrender.com",
    "anime-manga.jp",
    "anime-planet.com",
    "aopg-calculator.onrender.com",
    "apple.com",
    "arlevard.com",
    "art-mate.net",
    "artandpiece.com",
    "asurascans.com",
    "auffenbergfarmington.com",
    "authgo.fly.dev",
    "autostreamtest.onrender.com",
    "autozone.com",
    "axutongxue.onrender.com",
    "baidu.com",
    "bangumi.tv",
    "batomirrors.pages.dev",
    "baton-app-ea7b5.web.app",
    "bcd-app.fly.dev",
    "beinghongkong.com",
    "bhuntr.com",
    "bibliocommons.com",
    "bilibili-evolved-doc.vercel.app",
    "bilibili.com",
    "blog-ffzz.vercel.app",
    "blog.replit.com",
    "bmcomic.com",
    "bmwfwb.com",
    "bomtoon.tw",
    "bookbaby.com",
    "bookmanta.com",
    "britannica.com",
    "britishmuseum.org",
    "brooklynmuseum.org",
    "bsky.app",
    "bskyinfo.com",
    "bungatiga.onrender.com",
    "bzmanga.com",
    "cambridge.org",
    "cancheo-web.fly.dev",
    "carriersource.io",
    "cathaypacific.com",
    "cbr.com",
    "chamberofcommerce.com",
    "chunghwabookstore.com",
    "cinebai.onrender.com",
    "cinenoir.net",
    "circleboom.com",
    "civiltutorials.com",
    "clip-studio.com",
    "cltapp.fly.dev",
    "cm3721.com",
    "cmoa.jp",
    "co.jp",
    "co.uk",
    "collinsdictionary.com",
    "com.au",
    "com.cn",
    "com.hk",
    "com.mx",
    "com.tw",
    "com.uy",
    "comedy-mastermind.onrender.com",
    "comic-con.org",
    "comic-ogyaaa.com",
    "comic-walker.com",
    "comicavenue.hk",
    "comicbunch-kai.com",
    "comicpash.jp",
    "comicscenter.net",
    "comicstrap.com",
    "comix.to",
    "corocoro.jp",
    "creative-comic.tw",
    "crunchyroll.com",
    "cssn.cn",
    "ctext.org",
    "culture.tw",
    "cybo.com",
    "cyol.com",
    "cyzone.cn",
    "czn-save-cal.web.app",
    "d-dmm.com",
    "d1hl9setcycg81.cloudfront.net",
    "d1na3f9tshcp4p.cloudfront.net",
    "d1s8wm47asyysy.cloudfront.net",
    "d31a8rdj19i5e2.cloudfront.net",
    "d3aoa10o0410wd.cloudfront.net",
    "d3ra9nqn08kl2e.cloudfront.net",
    "d6lvl8l2l26yp.cloudfront.net",
    "darkhorse.com",
    "dc.com",
    "dealmoon.com",
    "debbieohi.com",
    "devault-app.fly.dev",
    "dictionary.com",
    "dirijasehistorial.com",
    "discsmijr8t6l.cloudfront.net",
    "dm5.com",
    "dmanshe.com",
    "dmo-market.onrender.com",
    "dnjtwtgi48217.cloudfront.net",
    "doc-openvideo.vercel.app",
    "docs.replit.com",
    "dokumanhk.net",
    "dokumanhkshop.com",
    "dongjian.vercel.app",
    "dongmanmanhua.cn",
    "douban.com",
    "douyin.com",
    "dpz3pzoteix4e.cloudfront.net",
    "easternshoretoyota.com",
    "ebay.com",
    "edu.hk",
    "edu.tw",
    "engineerfix.com",
    "english4u.net",
    "eslite.com",
    "exview.vercel.app",
    "facebook.com",
    "fandom.com",
    "fate-go.jp",
    "fatimae-and-louie.web.app",
    "ferreteriasuy.com",
    "find-open.com",
    "fleur-collections.com",
    "fly-changelog.fly.dev",
    "flyio-landing.fly.dev",
    "fmf-internal-app.onrender.com",
    "foreigh.com",
    "fredericwi.com",
    "freecomicbookday.com",
    "friday.tw",
    "futonapp.pages.dev",
    "fvtt-cn.vercel.app",
    "gamerant.com",
    "gamersky.com",
    "gazoaetns.onrender.com",
    "get-newfolders-here.fly.dev",
    "getbluepilot.com",
    "getskyscraper.com",
    "github.com",
    "glli-us.org",
    "go.jp",
    "gob.mx",
    "goodreads.com",
    "google.com",
    "gosgc.com",
    "gov.cn",
    "gov.hk",
    "gov.tw",
    "gov.uk",
    "guancha.cn",
    "gugu3.com",
    "gznf.net",
    "hahow.in",
    "haoduoman.com",
    "heartivetv.pages.dev",
    "hemh.cc",
    "heritage.museum",
    "hindustantimes.com",
    "history.com",
    "hk01.com",
    "hkcna.hk",
    "hkcsp.hk",
    "hkdance.com",
    "hkmemory.hk",
    "hkwl.org",
    "hoopladigital.com",
    "hoyoverse.com",
    "hp-gamma-eight.vercel.app",
    "huxiu.com",
    "hwxnet.com",
    "icctutorial.pages.dev",
    "ichefpos.com",
    "icy-veins.com",
    "ijfans.org",
    "imdb.com",
    "indigo.ca",
    "infinitiofmelbourne.com",
    "infobel.com",
    "inkr.com",
    "instagram.com",
    "iq.com",
    "iqiyi.com",
    "irothordertracker-4.onrender.com",
    "jiemian.com",
    "jisho.org",
    "johnleemazda.com",
    "jstor.org",
    "jump-mangasho.com",
    "junyiacademy.org",
    "justanswer.com",
    "k-manga.jp",
    "kadokawaworldmanga.com",
    "kalamanhua.com",
    "kaynscan.org",
    "kickstarter.com",
    "kilamanbo.world",
    "kleox99.github.io",
    "klook.com",
    "kobo.com",
    "kodansha.com",
    "komiic.com",
    "kuaikanmanhua.com",
    "kyotomm.jp",
    "laceanddaggerbooks.com",
    "lamangaclub.com",
    "landing-futon.pages.dev",
    "ldplayer.net",
    "learn.replit.com",
    "lego.com",
    "letschuhai.com",
    "librarything.com",
    "linkedin.com",
    "links.replit.com",
    "live.com",
    "lmanhua.com",
    "locuspublishing.com",
    "m21.hk",
    "manga-barcelona.com",
    "manga-comic-con.de",
    "manga-go.pages.dev",
    "manga-mee.jp",
    "manga-shinchan.com",
    "manga-up.com",
    "mangacopy.com",
    "mangadass.com",
    "mangahelpers.com",
    "mangapark.page",
    "mangashare.vercel.app",
    "mangogo.pages.dev",
    "manhai.cc",
    "manhuagui.com",
    "manhuaplus.com",
    "manhuaren.com",
    "manhuascan.my",
    "manhuato.com",
    "manhuatop.org",
    "manhuatuan.com",
    "manhuaus.club",
    "manhuaus.com",
    "manhwahq.com",
    "manqianhui.com",
    "manqumanhua.com",
    "mapquest.com",
    "marist.edu",
    "marvel.com",
    "matterapp.com",
    "mechacomic.jp",
    "medium.com",
    "mercedesbenzsouthorlando.com",
    "merriam-webster.com",
    "mgread.io",
    "microsoft.com",
    "miguapp.pages.dev",
    "mihcm.com",
    "mingpao.com",
    "mirrormedia.mg",
    "miyomi.pages.dev",
    "mojoin.com",
    "moyud.vercel.app",
    "mpweekly.com",
    "mubai.link",
    "mvdgestiona.uy",
    "myanimelist.net",
    "mycomic.com",
    "mystore411.com",
    "mythwright.fly.dev",
    "neocha.com",
    "net.tw",
    "netflix.com",
    "news.cn",
    "newyorkcomiccon.com",
    "nickstember.com",
    "nintendo.com",
    "nmfta.org",
    "node-snapdrop.onrender.com",
    "novacircle.com",
    "nthulabook.onrender.com",
    "nypl.org",
    "oapen.org",
    "ocacnews.net",
    "octopusmanga.com",
    "office.com",
    "ofiii.com",
    "olympus.pages.dev",
    "or.jp",
    "orangenews.hk",
    "org.hk",
    "org.tw",
    "outlook.com",
    "parliament.uk",
    "parliamenttoday.com",
    "patreon.com",
    "pattern-playground.onrender.com",
    "pawakalabs.com",
    "pegasusels.com",
    "pejdw.com",
    "piccoma.com",
    "pinterest.com",
    "pixiv-reader.vercel.app",
    "pixiv-viewer.vercel.app",
    "playstation.com",
    "playtorrio.pages.dev",
    "plurk.com",
    "primevideo.com",
    "qianchuan.onrender.com",
    "qq.com",
    "quire-comic.com",
    "quora.com",
    "readmoo.com",
    "reddit.com",
    "references.fly.dev",
    "replit.com",
    "reseau-fouineurs.onrender.com",
    "rinkocomics.com",
    "rit.vercel.app",
    "roaminglife.tw",
    "romparty.fly.dev",
    "rottentomatoes.com",
    "roumanhua.net",
    "rthk.hk",
    "rule34dle.vercel.app",
    "sadg166.pages.dev",
    "sat.cool",
    "seer-calculator.onrender.com",
    "sevenseasentertainment.com",
    "sg.vercel.app",
    "sheraton-taitung.com",
    "shonenjumpplus.com",
    "shonenmagazine.com",
    "shopee.tw",
    "shoplineapp.com",
    "sina.cn",
    "slashgear.com",
    "smallbiztrends.com",
    "socialwalls.com",
    "sodehiku.web.app",
    "sohu.com",
    "sothebys.com",
    "sounova.com",
    "spotify.com",
    "stackexchange.com",
    "stackoverflow.com",
    "status.replit.com",
    "stdaily.com",
    "storebranch.com",
    "storeopeninghours.com",
    "studiocity-macau.com",
    "studiom.fly.dev",
    "surveymonkey.com",
    "sustainability-directory.com",
    "taicca.tw",
    "taiwan-panorama.com",
    "taiwanngo.tw",
    "taobao.com",
    "taptap.cn",
    "tcb.tw",
    "techvyro-movies.onrender.com",
    "th3-anime.pages.dev",
    "theflix.vercel.app",
    "thefreedictionary.com",
    "thegradcafe.com",
    "thepaper.cn",
    "thew1london.com",
    "thinkingtaiwan.net",
    "thisbigwildworld.com",
    "thivien.net",
    "threads.com",
    "tiktok.com",
    "tkww.hk",
    "to-corona-ex.com",
    "tohray.fly.dev",
    "toonverse.net",
    "topmanhua.fan",
    "toptoon.net",
    "tracyminifigs.com",
    "travelers.com",
    "ts4rebels-info-page.onrender.com",
    "tvtropes.org",
    "twreporter.org",
    "twstay.com",
    "ubereats.com",
    "ucpress.edu",
    "udn.com",
    "umeadow.com",
    "umich.edu",
    "un.org",
    "unblockthetruth.onrender.com",
    "uniqlo.com",
    "unmiraclepourlafrance.onrender.com",
    "uptodown.com",
    "uruguaypymes.com",
    "us.com",
    "usdictionary.com",
    "v2ex.vercel.app",
    "valamis.com",
    "verifiedcarrier.com",
    "verifycarrier.com",
    "viz.com",
    "vocus.cc",
    "vortexscans.org",
    "walls.io",
    "walmart.com",
    "wanikani.com",
    "webtoons.com",
    "weibo.com",
    "weimh.com",
    "wenweipo.com",
    "whatsapp.com",
    "whb.cn",
    "wikipedia.org",
    "wiktionary.org",
    "wmanhua.com",
    "wooey.fly.dev",
    "wooky.fly.dev",
    "wordsanswers.info",
    "wrenly.ai",
    "xbox.com",
    "xiangchuifeng-github-io.vercel.app",
    "xiaotou.vercel.app",
    "xiehuio.com",
    "xinhuanet.com",
    "xinmanhua.net",
    "yahoo.com",
    "yfsp.tv",
    "yicai.com",
    "yinghuaanime.com",
    "youtube.com",
    "zamgot-dev.fly.dev",
    "zamgot-studio-dev.fly.dev",
    "zdic.net",
    "zhihu.com",
    "zillow.com",
    "zymk.cn",
    "zzz-run-archive.onrender.com"
  ],
  "removedDomains": [
    {
      "domain": "topmanhua.fan",
      "reason": "no_indicators",
      "detail": "",
      "matched_kw": ""
    },
    {
      "domain": "asurascans.com",
      "reason": "no_indicators",
      "detail": "",
      "matched_kw": ""
    },
    {
      "domain": "toonverse.net",
      "reason": "no_indicators",
      "detail": "",
      "matched_kw": ""
    },
    {
      "domain": "wikipedia.org",
      "reason": "no_indicators",
      "detail": "",
      "matched_kw": ""
    },
    {
      "domain": "manhuato.com",
      "reason": "no_indicators",
      "detail": "",
      "matched_kw": ""
    },
    {
      "domain": "manhuaus.com",
      "reason": "network_issue",
      "detail": "http_403",
      "matched_kw": ""
    },
    {
      "domain": "octopusmanga.com",
      "reason": "no_indicators",
      "detail": "",
      "matched_kw": ""
    },
    {
      "domain": "reddit.com",
      "reason": "network_issue",
      "detail": "http_403",
      "matched_kw": ""
    },
    {
      "domain": "mgread.io",
      "reason": "anti_pattern",
      "detail": "",
      "matched_kw": "18+"
    },
    {
      "domain": "manhuaplus.com",
      "reason": "no_indicators",
      "detail": "",
      "matched_kw": ""
    },
    {
      "domain": "youtube.com",
      "reason": "no_indicators",
      "detail": "",
      "matched_kw": ""
    },
    {
      "domain": "laceanddaggerbooks.com",
      "reason": "no_indicators",
      "detail": "",
      "matched_kw": ""
    },
    {
      "domain": "co.uk",
      "reason": "network_issue",
      "detail": "fetch_failed:HTTPSConnectionPool(host='co.uk', port=443): Max retries exceeded with url: / (Caused by NameResolutionError(\"HTTPSConnection(host='co.uk', port=443): Failed to resolve 'co.uk' ([Errno -5] No address associated with hostname)\"))",
      "matched_kw": ""
    },
    {
      "domain": "medium.com",
      "reason": "network_issue",
      "detail": "http_403",
      "matched_kw": ""
    },
    {
      "domain": "manhwahq.com",
      "reason": "no_indicators",
      "detail": "",
      "matched_kw": ""
    },
    {
      "domain": "inkr.com",
      "reason": "no_indicators",
      "detail": "",
      "matched_kw": ""
    },
    {
      "domain": "rinkocomics.com",
      "reason": "no_indicators",
      "detail": "",
      "matched_kw": ""
    },
    {
      "domain": "vortexscans.org",
      "reason": "no_indicators",
      "detail": "",
      "matched_kw": ""
    },
    {
      "domain": "mangadass.com",
      "reason": "no_indicators",
      "detail": "",
      "matched_kw": ""
    },
    {
      "domain": "mangapark.page",
      "reason": "no_indicators",
      "detail": "",
      "matched_kw": ""
    },
    {
      "domain": "fandom.com",
      "reason": "network_issue",
      "detail": "http_403",
      "matched_kw": ""
    },
    {
      "domain": "jstor.org",
      "reason": "no_indicators",
      "detail": "",
      "matched_kw": ""
    },
    {
      "domain": "quora.com",
      "reason": "network_issue",
      "detail": "http_403",
      "matched_kw": ""
    },
    {
      "domain": "goodreads.com",
      "reason": "no_indicators",
      "detail": "",
      "matched_kw": ""
    },
    {
      "domain": "umich.edu",
      "reason": "network_issue",
      "detail": "http_403",
      "matched_kw": ""
    },
    {
      "domain": "bookbaby.com",
      "reason": "no_indicators",
      "detail": "",
      "matched_kw": ""
    },
    {
      "domain": "kickstarter.com",
      "reason": "network_issue",
      "detail": "http_403",
      "matched_kw": ""
    },
    {
      "domain": "oapen.org",
      "reason": "network_issue",
      "detail": "http_403",
      "matched_kw": ""
    },
    {
      "domain": "cbr.com",
      "reason": "no_indicators",
      "detail": "",
      "matched_kw": ""
    },
    {
      "domain": "glli-us.org",
      "reason": "no_indicators",
      "detail": "",
      "matched_kw": ""
    },
    {
      "domain": "pinterest.com",
      "reason": "no_indicators",
      "detail": "",
      "matched_kw": ""
    },
    {
      "domain": "myanimelist.net",
      "reason": "no_indicators",
      "detail": "",
      "matched_kw": ""
    },
    {
      "domain": "librarything.com",
      "reason": "network_issue",
      "detail": "http_403",
      "matched_kw": ""
    },
    {
      "domain": "amazon.com",
      "reason": "no_indicators",
      "detail": "",
      "matched_kw": ""
    },
    {
      "domain": "stackexchange.com",
      "reason": "no_indicators",
      "detail": "",
      "matched_kw": ""
    },
    {
      "domain": "wiktionary.org",
      "reason": "no_indicators",
      "detail": "",
      "matched_kw": ""
    },
    {
      "domain": "sothebys.com",
      "reason": "no_indicators",
      "detail": "",
      "matched_kw": ""
    },
    {
      "domain": "pawakalabs.com",
      "reason": "no_indicators",
      "detail": "",
      "matched_kw": ""
    },
    {
      "domain": "anime-planet.com",
      "reason": "no_indicators",
      "detail": "",
      "matched_kw": ""
    },
    {
      "domain": "manhuascan.my",
      "reason": "anti_pattern",
      "detail": "",
      "matched_kw": "18+"
    },
    {
      "domain": "facebook.com",
      "reason": "network_issue",
      "detail": "http_400",
      "matched_kw": ""
    },
    {
      "domain": "neocha.com",
      "reason": "no_indicators",
      "detail": "",
      "matched_kw": ""
    },
    {
      "domain": "bibliocommons.com",
      "reason": "no_indicators",
      "detail": "",
      "matched_kw": ""
    },
    {
      "domain": "sevenseasentertainment.com",
      "reason": "network_issue",
      "detail": "http_403",
      "matched_kw": ""
    },
    {
      "domain": "pegasusels.com",
      "reason": "no_indicators",
      "detail": "",
      "matched_kw": ""
    },
    {
      "domain": "taiwan-panorama.com",
      "reason": "network_issue",
      "detail": "http_404",
      "matched_kw": ""
    },
    {
      "domain": "uptodown.com",
      "reason": "no_indicators",
      "detail": "",
      "matched_kw": ""
    },
    {
      "domain": "comix.to",
      "reason": "no_indicators",
      "detail": "",
      "matched_kw": ""
    },
    {
      "domain": "instagram.com",
      "reason": "no_indicators",
      "detail": "",
      "matched_kw": ""
    },
    {
      "domain": "tiktok.com",
      "reason": "content_blocked",
      "detail": "",
      "matched_kw": "购物"
    },
    {
      "domain": "marist.edu",
      "reason": "no_indicators",
      "detail": "",
      "matched_kw": ""
    },
    {
      "domain": "tvtropes.org",
      "reason": "no_indicators",
      "detail": "",
      "matched_kw": ""
    },
    {
      "domain": "ucpress.edu",
      "reason": "no_indicators",
      "detail": "",
      "matched_kw": ""
    },
    {
      "domain": "hindustantimes.com",
      "reason": "no_indicators",
      "detail": "",
      "matched_kw": ""
    },
    {
      "domain": "gamerant.com",
      "reason": "no_indicators",
      "detail": "",
      "matched_kw": ""
    },
    {
      "domain": "kaynscan.org",
      "reason": "no_indicators",
      "detail": "",
      "matched_kw": ""
    },
    {
      "domain": "walmart.com",
      "reason": "no_indicators",
      "detail": "",
      "matched_kw": ""
    },
    {
      "domain": "mangahelpers.com",
      "reason": "no_indicators",
      "detail": "",
      "matched_kw": ""
    },
    {
      "domain": "com.au",
      "reason": "network_issue",
      "detail": "fetch_failed:HTTPSConnectionPool(host='com.au', port=443): Max retries exceeded with url: / (Caused by NameResolutionError(\"HTTPSConnection(host='com.au', port=443): Failed to resolve 'com.au' ([Errno -5] No address associated with hostname)\"))",
      "matched_kw": ""
    },
    {
      "domain": "manhuaus.club",
      "reason": "no_indicators",
      "detail": "",
      "matched_kw": ""
    },
    {
      "domain": "com.mx",
      "reason": "network_issue",
      "detail": "fetch_failed:HTTPSConnectionPool(host='com.mx', port=443): Max retries exceeded with url: / (Caused by NameResolutionError(\"HTTPSConnection(host='com.mx', port=443): Failed to resolve 'com.mx' ([Errno -5] No address associated with hostname)\"))",
      "matched_kw": ""
    },
    {
      "domain": "manhuatop.org",
      "reason": "no_indicators",
      "detail": "",
      "matched_kw": ""
    },
    {
      "domain": "imdb.com",
      "reason": "no_indicators",
      "detail": "",
      "matched_kw": ""
    },
    {
      "domain": "edu.tw",
      "reason": "network_issue",
      "detail": "fetch_failed:HTTPSConnectionPool(host='edu.tw', port=443): Max retries exceeded with url: / (Caused by NameResolutionError(\"HTTPSConnection(host='edu.tw', port=443): Failed to resolve 'edu.tw' ([Errno -5] No address associated with hostname)\"))",
      "matched_kw": ""
    },
    {
      "domain": "cinenoir.net",
      "reason": "no_indicators",
      "detail": "",
      "matched_kw": ""
    },
    {
      "domain": "jisho.org",
      "reason": "no_indicators",
      "detail": "",
      "matched_kw": ""
    },
    {
      "domain": "history.com",
      "reason": "no_indicators",
      "detail": "",
      "matched_kw": ""
    },
    {
      "domain": "baidu.com",
      "reason": "anti_pattern",
      "detail": "",
      "matched_kw": "18r"
    },
    {
      "domain": "spotify.com",
      "reason": "no_indicators",
      "detail": "",
      "matched_kw": ""
    },
    {
      "domain": "google.com",
      "reason": "no_indicators",
      "detail": "",
      "matched_kw": ""
    },
    {
      "domain": "hwxnet.com",
      "reason": "network_issue",
      "detail": "fetch_failed:HTTPSConnectionPool(host='hwxnet.com', port=443): Max retries exceeded with url: / (Caused by NameResolutionError(\"HTTPSConnection(host='hwxnet.com', port=443): Failed to resolve 'hwxnet.com' ([Errno -2] Name or service not known)\"))",
      "matched_kw": ""
    },
    {
      "domain": "ctext.org",
      "reason": "content_blocked",
      "detail": "",
      "matched_kw": "教育"
    },
    {
      "domain": "dongmanmanhua.cn",
      "reason": "content_blocked",
      "detail": "",
      "matched_kw": "教育"
    },
    {
      "domain": "marvel.com",
      "reason": "no_indicators",
      "detail": "",
      "matched_kw": ""
    },
    {
      "domain": "wanikani.com",
      "reason": "no_indicators",
      "detail": "",
      "matched_kw": ""
    },
    {
      "domain": "rottentomatoes.com",
      "reason": "no_indicators",
      "detail": "",
      "matched_kw": ""
    },
    {
      "domain": "netflix.com",
      "reason": "no_indicators",
      "detail": "",
      "matched_kw": ""
    },
    {
      "domain": "primevideo.com",
      "reason": "no_indicators",
      "detail": "",
      "matched_kw": ""
    },
    {
      "domain": "apple.com",
      "reason": "no_indicators",
      "detail": "",
      "matched_kw": ""
    },
    {
      "domain": "edu.hk",
      "reason": "network_issue",
      "detail": "fetch_failed:HTTPSConnectionPool(host='edu.hk', port=443): Max retries exceeded with url: / (Caused by NameResolutionError(\"HTTPSConnection(host='edu.hk', port=443): Failed to resolve 'edu.hk' ([Errno -5] No address associated with hostname)\"))",
      "matched_kw": ""
    },
    {
      "domain": "gov.tw",
      "reason": "anti_pattern",
      "detail": "",
      "matched_kw": "18+"
    },
    {
      "domain": "zymk.cn",
      "reason": "network_issue",
      "detail": "fetch_failed:HTTPSConnectionPool(host='zymk.cn', port=443): Max retries exceeded with url: / (Caused by SSLError(SSLCertVerificationError(1, \"[SSL: CERTIFICATE_VERIFY_FAILED] certificate verify failed: Hostname mismatch, certificate is not valid for 'zymk.cn'. (_ssl.c:1016)\")))",
      "matched_kw": ""
    },
    {
      "domain": "zdic.net",
      "reason": "no_indicators",
      "detail": "",
      "matched_kw": ""
    },
    {
      "domain": "bhuntr.com",
      "reason": "no_indicators",
      "detail": "",
      "matched_kw": ""
    },
    {
      "domain": "hkcsp.hk",
      "reason": "network_issue",
      "detail": "fetch_failed:HTTPSConnectionPool(host='hkcsp.hk', port=443): Max retries exceeded with url: / (Caused by SSLError(SSLError(1, '[SSL: TLSV1_ALERT_INTERNAL_ERROR] tlsv1 alert internal error (_ssl.c:1016)')))",
      "matched_kw": ""
    },
    {
      "domain": "twreporter.org",
      "reason": "content_blocked",
      "detail": "",
      "matched_kw": "基金"
    },
    {
      "domain": "org.hk",
      "reason": "network_issue",
      "detail": "fetch_failed:HTTPSConnectionPool(host='org.hk', port=443): Max retries exceeded with url: / (Caused by NameResolutionError(\"HTTPSConnection(host='org.hk', port=443): Failed to resolve 'org.hk' ([Errno -5] No address associated with hostname)\"))",
      "matched_kw": ""
    },
    {
      "domain": "manqumanhua.com",
      "reason": "no_indicators",
      "detail": "",
      "matched_kw": ""
    },
    {
      "domain": "com.tw",
      "reason": "network_issue",
      "detail": "fetch_failed:HTTPSConnectionPool(host='com.tw', port=443): Max retries exceeded with url: / (Caused by NameResolutionError(\"HTTPSConnection(host='com.tw', port=443): Failed to resolve 'com.tw' ([Errno -5] No address associated with hostname)\"))",
      "matched_kw": ""
    },
    {
      "domain": "roaminglife.tw",
      "reason": "network_issue",
      "detail": "fetch_failed:HTTPSConnectionPool(host='roaminglife.tw', port=443): Max retries exceeded with url: / (Caused by NameResolutionError(\"HTTPSConnection(host='roaminglife.tw', port=443): Failed to resolve 'roaminglife.tw' ([Errno -5] No address associated with hostname)\"))",
      "matched_kw": ""
    },
    {
      "domain": "org.tw",
      "reason": "network_issue",
      "detail": "fetch_failed:HTTPSConnectionPool(host='org.tw', port=443): Max retries exceeded with url: / (Caused by NameResolutionError(\"HTTPSConnection(host='org.tw', port=443): Failed to resolve 'org.tw' ([Errno -5] No address associated with hostname)\"))",
      "matched_kw": ""
    },
    {
      "domain": "thivien.net",
      "reason": "no_indicators",
      "detail": "",
      "matched_kw": ""
    },
    {
      "domain": "junyiacademy.org",
      "reason": "content_blocked",
      "detail": "",
      "matched_kw": "直播"
    },
    {
      "domain": "dmanshe.com",
      "reason": "no_indicators",
      "detail": "",
      "matched_kw": ""
    },
    {
      "domain": "sheraton-taitung.com",
      "reason": "network_issue",
      "detail": "fetch_failed:HTTPSConnectionPool(host='sheraton-taitung.com', port=443): Max retries exceeded with url: / (Caused by NameResolutionError(\"HTTPSConnection(host='sheraton-taitung.com', port=443): Failed to resolve 'sheraton-taitung.com' ([Errno -5] No address associated with hostname)\"))",
      "matched_kw": ""
    },
    {
      "domain": "manhai.cc",
      "reason": "no_indicators",
      "detail": "",
      "matched_kw": ""
    },
    {
      "domain": "com.cn",
      "reason": "network_issue",
      "detail": "fetch_failed:HTTPSConnectionPool(host='com.cn', port=443): Max retries exceeded with url: / (Caused by NameResolutionError(\"HTTPSConnection(host='com.cn', port=443): Failed to resolve 'com.cn' ([Errno -5] No address associated with hostname)\"))",
      "matched_kw": ""
    },
    {
      "domain": "studiocity-macau.com",
      "reason": "no_indicators",
      "detail": "",
      "matched_kw": ""
    },
    {
      "domain": "2k.com",
      "reason": "network_issue",
      "detail": "http_403",
      "matched_kw": ""
    },
    {
      "domain": "bmcomic.com",
      "reason": "no_indicators",
      "detail": "",
      "matched_kw": ""
    },
    {
      "domain": "taicca.tw",
      "reason": "content_blocked",
      "detail": "",
      "matched_kw": "金融"
    },
    {
      "domain": "bilibili.com",
      "reason": "content_blocked",
      "detail": "",
      "matched_kw": "房产"
    },
    {
      "domain": "un.org",
      "reason": "content_blocked",
      "detail": "",
      "matched_kw": "基金"
    },
    {
      "domain": "kilamanbo.world",
      "reason": "content_blocked",
      "detail": "",
      "matched_kw": "直播"
    },
    {
      "domain": "comicstrap.com",
      "reason": "network_issue",
      "detail": "fetch_failed:HTTPSConnectionPool(host='comicstrap.com', port=443): Max retries exceeded with url: / (Caused by SSLError(SSLCertVerificationError(1, '[SSL: CERTIFICATE_VERIFY_FAILED] certificate verify failed: self-signed certificate (_ssl.c:1016)')))",
      "matched_kw": ""
    },
    {
      "domain": "playstation.com",
      "reason": "no_indicators",
      "detail": "",
      "matched_kw": ""
    },
    {
      "domain": "manqianhui.com",
      "reason": "no_indicators",
      "detail": "",
      "matched_kw": ""
    },
    {
      "domain": "news.cn",
      "reason": "content_blocked",
      "detail": "",
      "matched_kw": "政府"
    },
    {
      "domain": "lego.com",
      "reason": "network_issue",
      "detail": "http_403",
      "matched_kw": ""
    },
    {
      "domain": "gov.cn",
      "reason": "network_issue",
      "detail": "fetch_failed:HTTPSConnectionPool(host='gov.cn', port=443): Max retries exceeded with url: / (Caused by NameResolutionError(\"HTTPSConnection(host='gov.cn', port=443): Failed to resolve 'gov.cn' ([Errno -5] No address associated with hostname)\"))",
      "matched_kw": ""
    },
    {
      "domain": "iq.com",
      "reason": "no_indicators",
      "detail": "",
      "matched_kw": ""
    },
    {
      "domain": "cmoa.jp",
      "reason": "network_issue",
      "detail": "fetch_failed:HTTPSConnectionPool(host='cmoa.jp', port=443): Max retries exceeded with url: / (Caused by NameResolutionError(\"HTTPSConnection(host='cmoa.jp', port=443): Failed to resolve 'cmoa.jp' ([Errno -5] No address associated with hostname)\"))",
      "matched_kw": ""
    },
    {
      "domain": "haoduoman.com",
      "reason": "content_blocked",
      "detail": "",
      "matched_kw": "留学"
    },
    {
      "domain": "wmanhua.com",
      "reason": "network_issue",
      "detail": "fetch_failed:HTTPSConnectionPool(host='wmanhua.com', port=443): Max retries exceeded with url: / (Caused by NameResolutionError(\"HTTPSConnection(host='wmanhua.com', port=443): Failed to resolve 'wmanhua.com' ([Errno -5] No address associated with hostname)\"))",
      "matched_kw": ""
    },
    {
      "domain": "bzmanga.com",
      "reason": "content_blocked",
      "detail": "",
      "matched_kw": "体育"
    },
    {
      "domain": "qq.com",
      "reason": "content_blocked",
      "detail": "",
      "matched_kw": "政府"
    },
    {
      "domain": "webtoons.com",
      "reason": "no_indicators",
      "detail": "",
      "matched_kw": ""
    },
    {
      "domain": "viz.com",
      "reason": "no_indicators",
      "detail": "",
      "matched_kw": ""
    },
    {
      "domain": "ac.jp",
      "reason": "network_issue",
      "detail": "fetch_failed:HTTPSConnectionPool(host='ac.jp', port=443): Max retries exceeded with url: / (Caused by NameResolutionError(\"HTTPSConnection(host='ac.jp', port=443): Failed to resolve 'ac.jp' ([Errno -5] No address associated with hostname)\"))",
      "matched_kw": ""
    },
    {
      "domain": "k-manga.jp",
      "reason": "network_issue",
      "detail": "fetch_failed:HTTPSConnectionPool(host='k-manga.jp', port=443): Max retries exceeded with url: / (Caused by ConnectTimeoutError(<HTTPSConnection(host='k-manga.jp', port=443) at 0x7fc28154f450>, 'Connection to k-manga.jp timed out. (connect timeout=10)'))",
      "matched_kw": ""
    },
    {
      "domain": "nypl.org",
      "reason": "anti_pattern",
      "detail": "",
      "matched_kw": "18r"
    },
    {
      "domain": "kuaikanmanhua.com",
      "reason": "anti_pattern",
      "detail": "",
      "matched_kw": "成人"
    },
    {
      "domain": "dc.com",
      "reason": "no_indicators",
      "detail": "",
      "matched_kw": ""
    },
    {
      "domain": "co.jp",
      "reason": "network_issue",
      "detail": "fetch_failed:HTTPSConnectionPool(host='co.jp', port=443): Max retries exceeded with url: / (Caused by NameResolutionError(\"HTTPSConnection(host='co.jp', port=443): Failed to resolve 'co.jp' ([Errno -5] No address associated with hostname)\"))",
      "matched_kw": ""
    },
    {
      "domain": "github.com",
      "reason": "no_indicators",
      "detail": "",
      "matched_kw": ""
    },
    {
      "domain": "brooklynmuseum.org",
      "reason": "network_issue",
      "detail": "http_429",
      "matched_kw": ""
    },
    {
      "domain": "crunchyroll.com",
      "reason": "no_indicators",
      "detail": "",
      "matched_kw": ""
    },
    {
      "domain": "kyotomm.jp",
      "reason": "no_indicators",
      "detail": "",
      "matched_kw": ""
    },
    {
      "domain": "go.jp",
      "reason": "network_issue",
      "detail": "fetch_failed:HTTPSConnectionPool(host='go.jp', port=443): Max retries exceeded with url: / (Caused by NameResolutionError(\"HTTPSConnection(host='go.jp', port=443): Failed to resolve 'go.jp' ([Errno -5] No address associated with hostname)\"))",
      "matched_kw": ""
    },
    {
      "domain": "britishmuseum.org",
      "reason": "network_issue",
      "detail": "http_403",
      "matched_kw": ""
    },
    {
      "domain": "kadokawaworldmanga.com",
      "reason": "no_indicators",
      "detail": "",
      "matched_kw": ""
    },
    {
      "domain": "hoopladigital.com",
      "reason": "no_indicators",
      "detail": "",
      "matched_kw": ""
    },
    {
      "domain": "comic-con.org",
      "reason": "no_indicators",
      "detail": "",
      "matched_kw": ""
    },
    {
      "domain": "hoyoverse.com",
      "reason": "no_indicators",
      "detail": "",
      "matched_kw": ""
    },
    {
      "domain": "manga-comic-con.de",
      "reason": "no_indicators",
      "detail": "",
      "matched_kw": ""
    },
    {
      "domain": "readmoo.com",
      "reason": "network_issue",
      "detail": "http_403",
      "matched_kw": ""
    },
    {
      "domain": "nintendo.com",
      "reason": "no_indicators",
      "detail": "",
      "matched_kw": ""
    },
    {
      "domain": "eslite.com",
      "reason": "network_issue",
      "detail": "fetch_failed:HTTPSConnectionPool(host='eslite.com', port=443): Max retries exceeded with url: / (Caused by NameResolutionError(\"HTTPSConnection(host='eslite.com', port=443): Failed to resolve 'eslite.com' ([Errno -5] No address associated with hostname)\"))",
      "matched_kw": ""
    },
    {
      "domain": "kodansha.com",
      "reason": "no_indicators",
      "detail": "",
      "matched_kw": ""
    },
    {
      "domain": "lamangaclub.com",
      "reason": "no_indicators",
      "detail": "",
      "matched_kw": ""
    },
    {
      "domain": "comicscenter.net",
      "reason": "network_issue",
      "detail": "fetch_failed:HTTPSConnectionPool(host='comicscenter.net', port=443): Max retries exceeded with url: / (Caused by SSLError(SSLError(1, '[SSL: SSLV3_ALERT_HANDSHAKE_FAILURE] sslv3 alert handshake failure (_ssl.c:1016)')))",
      "matched_kw": ""
    },
    {
      "domain": "manga-up.com",
      "reason": "no_indicators",
      "detail": "",
      "matched_kw": ""
    },
    {
      "domain": "zhihu.com",
      "reason": "content_blocked",
      "detail": "",
      "matched_kw": "法律"
    },
    {
      "domain": "uniqlo.com",
      "reason": "no_indicators",
      "detail": "",
      "matched_kw": ""
    },
    {
      "domain": "kobo.com",
      "reason": "network_issue",
      "detail": "http_403",
      "matched_kw": ""
    },
    {
      "domain": "manga-barcelona.com",
      "reason": "no_indicators",
      "detail": "",
      "matched_kw": ""
    },
    {
      "domain": "freecomicbookday.com",
      "reason": "network_issue",
      "detail": "fetch_failed:HTTPSConnectionPool(host='freecomicbookday.com', port=443): Max retries exceeded with url: / (Caused by SSLError(SSLCertVerificationError(1, '[SSL: CERTIFICATE_VERIFY_FAILED] certificate verify failed: unable to get local issuer certificate (_ssl.c:1016)')))",
      "matched_kw": ""
    },
    {
      "domain": "ebay.com",
      "reason": "no_indicators",
      "detail": "",
      "matched_kw": ""
    },
    {
      "domain": "newyorkcomiccon.com",
      "reason": "no_indicators",
      "detail": "",
      "matched_kw": ""
    },
    {
      "domain": "or.jp",
      "reason": "network_issue",
      "detail": "fetch_failed:HTTPSConnectionPool(host='or.jp', port=443): Max retries exceeded with url: / (Caused by NameResolutionError(\"HTTPSConnection(host='or.jp', port=443): Failed to resolve 'or.jp' ([Errno -5] No address associated with hostname)\"))",
      "matched_kw": ""
    },
    {
      "domain": "indigo.ca",
      "reason": "no_indicators",
      "detail": "",
      "matched_kw": ""
    },
    {
      "domain": "shonenjumpplus.com",
      "reason": "no_indicators",
      "detail": "",
      "matched_kw": ""
    },
    {
      "domain": "fate-go.jp",
      "reason": "network_issue",
      "detail": "fetch_failed:HTTPSConnectionPool(host='fate-go.jp', port=443): Max retries exceeded with url: / (Caused by ConnectTimeoutError(<HTTPSConnection(host='fate-go.jp', port=443) at 0x7fc2815ffc90>, 'Connection to fate-go.jp timed out. (connect timeout=10)'))",
      "matched_kw": ""
    },
    {
      "domain": "comicpash.jp",
      "reason": "content_blocked",
      "detail": "",
      "matched_kw": "教育"
    },
    {
      "domain": "darkhorse.com",
      "reason": "no_indicators",
      "detail": "",
      "matched_kw": ""
    },
    {
      "domain": "mangacopy.com",
      "reason": "anti_pattern",
      "detail": "",
      "matched_kw": "18+"
    },
    {
      "domain": "yfsp.tv",
      "reason": "content_blocked",
      "detail": "",
      "matched_kw": "汽车"
    },
    {
      "domain": "douban.com",
      "reason": "content_blocked",
      "detail": "",
      "matched_kw": "电影"
    },
    {
      "domain": "mubai.link",
      "reason": "network_issue",
      "detail": "fetch_failed:HTTPSConnectionPool(host='mubai.link', port=443): Max retries exceeded with url: / (Caused by NameResolutionError(\"HTTPSConnection(host='mubai.link', port=443): Failed to resolve 'mubai.link' ([Errno -5] No address associated with hostname)\"))",
      "matched_kw": ""
    },
    {
      "domain": "friday.tw",
      "reason": "no_indicators",
      "detail": "",
      "matched_kw": ""
    },
    {
      "domain": "233dongman.com",
      "reason": "content_blocked",
      "detail": "",
      "matched_kw": "直播"
    },
    {
      "domain": "lmanhua.com",
      "reason": "content_blocked",
      "detail": "",
      "matched_kw": "金融"
    },
    {
      "domain": "sohu.com",
      "reason": "content_blocked",
      "detail": "",
      "matched_kw": "房产"
    },
    {
      "domain": "17173.com",
      "reason": "no_indicators",
      "detail": "",
      "matched_kw": ""
    },
    {
      "domain": "jiemian.com",
      "reason": "content_blocked",
      "detail": "",
      "matched_kw": "汽车"
    },
    {
      "domain": "iqiyi.com",
      "reason": "content_blocked",
      "detail": "",
      "matched_kw": "旅游"
    },
    {
      "domain": "taptap.cn",
      "reason": "no_indicators",
      "detail": "",
      "matched_kw": ""
    },
    {
      "domain": "10086.cn",
      "reason": "network_issue",
      "detail": "fetch_failed:HTTPSConnectionPool(host='10086.cn', port=443): Max retries exceeded with url: / (Caused by SSLError(SSLError(1, '[SSL: UNSAFE_LEGACY_RENEGOTIATION_DISABLED] unsafe legacy renegotiation disabled (_ssl.c:1016)')))",
      "matched_kw": ""
    },
    {
      "domain": "huxiu.com",
      "reason": "network_issue",
      "detail": "fetch_failed:HTTPSConnectionPool(host='m.huxiu.com', port=443): Read timed out.",
      "matched_kw": ""
    },
    {
      "domain": "36kr.com",
      "reason": "anti_pattern",
      "detail": "",
      "matched_kw": "18+"
    },
    {
      "domain": "taobao.com",
      "reason": "content_blocked",
      "detail": "",
      "matched_kw": "购物"
    },
    {
      "domain": "net.tw",
      "reason": "network_issue",
      "detail": "fetch_failed:HTTPSConnectionPool(host='net.tw', port=443): Max retries exceeded with url: / (Caused by NameResolutionError(\"HTTPSConnection(host='net.tw', port=443): Failed to resolve 'net.tw' ([Errno -5] No address associated with hostname)\"))",
      "matched_kw": ""
    },
    {
      "domain": "cyzone.cn",
      "reason": "no_indicators",
      "detail": "",
      "matched_kw": ""
    },
    {
      "domain": "anhuinews.com",
      "reason": "no_indicators",
      "detail": "",
      "matched_kw": ""
    },
    {
      "domain": "163.com",
      "reason": "content_blocked",
      "detail": "",
      "matched_kw": "编程"
    },
    {
      "domain": "cssn.cn",
      "reason": "no_indicators",
      "detail": "",
      "matched_kw": ""
    },
    {
      "domain": "weibo.com",
      "reason": "no_indicators",
      "detail": "",
      "matched_kw": ""
    },
    {
      "domain": "21jingji.com",
      "reason": "no_indicators",
      "detail": "",
      "matched_kw": ""
    },
    {
      "domain": "douyin.com",
      "reason": "no_indicators",
      "detail": "",
      "matched_kw": ""
    },
    {
      "domain": "sina.cn",
      "reason": "content_blocked",
      "detail": "",
      "matched_kw": "房产"
    },
    {
      "domain": "bangumi.tv",
      "reason": "no_indicators",
      "detail": "",
      "matched_kw": ""
    },
    {
      "domain": "cm3721.com",
      "reason": "content_blocked",
      "detail": "",
      "matched_kw": "政府"
    },
    {
      "domain": "stdaily.com",
      "reason": "no_indicators",
      "detail": "",
      "matched_kw": ""
    },
    {
      "domain": "whb.cn",
      "reason": "network_issue",
      "detail": "fetch_failed:HTTPSConnectionPool(host='whb.cn', port=443): Max retries exceeded with url: / (Caused by NameResolutionError(\"HTTPSConnection(host='whb.cn', port=443): Failed to resolve 'whb.cn' ([Errno -3] Temporary failure in name resolution)\"))",
      "matched_kw": ""
    },
    {
      "domain": "cyol.com",
      "reason": "no_indicators",
      "detail": "",
      "matched_kw": ""
    },
    {
      "domain": "dealmoon.com",
      "reason": "network_issue",
      "detail": "http_403",
      "matched_kw": ""
    },
    {
      "domain": "xinhuanet.com",
      "reason": "content_blocked",
      "detail": "",
      "matched_kw": "政府"
    },
    {
      "domain": "thepaper.cn",
      "reason": "network_issue",
      "detail": "http_403",
      "matched_kw": ""
    },
    {
      "domain": "patreon.com",
      "reason": "network_issue",
      "detail": "http_403",
      "matched_kw": ""
    },
    {
      "domain": "letschuhai.com",
      "reason": "anti_pattern",
      "detail": "",
      "matched_kw": "18r"
    },
    {
      "domain": "yicai.com",
      "reason": "network_issue",
      "detail": "fetch_failed:HTTPSConnectionPool(host='yicai.com', port=443): Max retries exceeded with url: / (Caused by ConnectTimeoutError(<HTTPSConnection(host='yicai.com', port=443) at 0x7fc281499890>, 'Connection to yicai.com timed out. (connect timeout=10)'))",
      "matched_kw": ""
    },
    {
      "domain": "slashgear.com",
      "reason": "no_indicators",
      "detail": "",
      "matched_kw": ""
    },
    {
      "domain": "justanswer.com",
      "reason": "network_issue",
      "detail": "http_403",
      "matched_kw": ""
    },
    {
      "domain": "auffenbergfarmington.com",
      "reason": "network_issue",
      "detail": "http_403",
      "matched_kw": ""
    },
    {
      "domain": "infinitiofmelbourne.com",
      "reason": "no_indicators",
      "detail": "",
      "matched_kw": ""
    },
    {
      "domain": "bmwfwb.com",
      "reason": "network_issue",
      "detail": "http_403",
      "matched_kw": ""
    },
    {
      "domain": "engineerfix.com",
      "reason": "no_indicators",
      "detail": "",
      "matched_kw": ""
    },
    {
      "domain": "komiic.com",
      "reason": "no_indicators",
      "detail": "",
      "matched_kw": ""
    },
    {
      "domain": "mercedesbenzsouthorlando.com",
      "reason": "network_issue",
      "detail": "http_403",
      "matched_kw": ""
    },
    {
      "domain": "johnleemazda.com",
      "reason": "no_indicators",
      "detail": "",
      "matched_kw": ""
    },
    {
      "domain": "easternshoretoyota.com",
      "reason": "network_issue",
      "detail": "fetch_failed:HTTPSConnectionPool(host='easternshoretoyota.com', port=443): Max retries exceeded with url: / (Caused by ConnectTimeoutError(<HTTPSConnection(host='easternshoretoyota.com', port=443) at 0x7fc28144a6d0>, 'Connection to easternshoretoyota.com timed out. (connect timeout=10)'))",
      "matched_kw": ""
    },
    {
      "domain": "pejdw.com",
      "reason": "network_issue",
      "detail": "fetch_failed:HTTPSConnectionPool(host='www.pejdw.com', port=443): Read timed out. (read timeout=10)",
      "matched_kw": ""
    },
    {
      "domain": "clip-studio.com",
      "reason": "network_issue",
      "detail": "http_403",
      "matched_kw": ""
    },
    {
      "domain": "xinmanhua.net",
      "reason": "no_indicators",
      "detail": "",
      "matched_kw": ""
    },
    {
      "domain": "anime-manga.jp",
      "reason": "no_indicators",
      "detail": "",
      "matched_kw": ""
    },
    {
      "domain": "yahoo.com",
      "reason": "no_indicators",
      "detail": "",
      "matched_kw": ""
    },
    {
      "domain": "english4u.net",
      "reason": "network_issue",
      "detail": "fetch_failed:HTTPSConnectionPool(host='english4u.net', port=443): Max retries exceeded with url: / (Caused by NameResolutionError(\"HTTPSConnection(host='english4u.net', port=443): Failed to resolve 'english4u.net' ([Errno -5] No address associated with hostname)\"))",
      "matched_kw": ""
    },
    {
      "domain": "tracyminifigs.com",
      "reason": "no_indicators",
      "detail": "",
      "matched_kw": ""
    },
    {
      "domain": "twstay.com",
      "reason": "no_indicators",
      "detail": "",
      "matched_kw": ""
    },
    {
      "domain": "sat.cool",
      "reason": "no_indicators",
      "detail": "",
      "matched_kw": ""
    },
    {
      "domain": "guancha.cn",
      "reason": "network_issue",
      "detail": "fetch_failed:HTTPSConnectionPool(host='guancha.cn', port=443): Max retries exceeded with url: / (Caused by NewConnectionError(\"HTTPSConnection(host='guancha.cn', port=443): Failed to establish a new connection: [Errno 111] Connection refused\"))",
      "matched_kw": ""
    },
    {
      "domain": "hahow.in",
      "reason": "no_indicators",
      "detail": "",
      "matched_kw": ""
    },
    {
      "domain": "ldplayer.net",
      "reason": "network_issue",
      "detail": "http_403",
      "matched_kw": ""
    },
    {
      "domain": "ichefpos.com",
      "reason": "content_blocked",
      "detail": "",
      "matched_kw": "教育"
    },
    {
      "domain": "ubereats.com",
      "reason": "content_blocked",
      "detail": "",
      "matched_kw": "导航"
    },
    {
      "domain": "hk01.com",
      "reason": "no_indicators",
      "detail": "",
      "matched_kw": ""
    },
    {
      "domain": "vocus.cc",
      "reason": "anti_pattern",
      "detail": "",
      "matched_kw": "成人"
    },
    {
      "domain": "shopee.tw",
      "reason": "no_indicators",
      "detail": "",
      "matched_kw": ""
    },
    {
      "domain": "heritage.museum",
      "reason": "network_issue",
      "detail": "fetch_failed:HTTPSConnectionPool(host='heritage.museum', port=443): Max retries exceeded with url: / (Caused by NameResolutionError(\"HTTPSConnection(host='heritage.museum', port=443): Failed to resolve 'heritage.museum' ([Errno -5] No address associated with hostname)\"))",
      "matched_kw": ""
    },
    {
      "domain": "manhuagui.com",
      "reason": "content_blocked",
      "detail": "",
      "matched_kw": "体育"
    },
    {
      "domain": "comicavenue.hk",
      "reason": "content_blocked",
      "detail": "",
      "matched_kw": "政府"
    },
    {
      "domain": "cathaypacific.com",
      "reason": "no_indicators",
      "detail": "",
      "matched_kw": ""
    },
    {
      "domain": "rthk.hk",
      "reason": "content_blocked",
      "detail": "",
      "matched_kw": "直播"
    },
    {
      "domain": "art-mate.net",
      "reason": "content_blocked",
      "detail": "",
      "matched_kw": "教育"
    },
    {
      "domain": "dokumanhkshop.com",
      "reason": "no_indicators",
      "detail": "",
      "matched_kw": ""
    },
    {
      "domain": "gov.hk",
      "reason": "network_issue",
      "detail": "fetch_failed:HTTPSConnectionPool(host='gov.hk', port=443): Max retries exceeded with url: / (Caused by NameResolutionError(\"HTTPSConnection(host='gov.hk', port=443): Failed to resolve 'gov.hk' ([Errno -5] No address associated with hostname)\"))",
      "matched_kw": ""
    },
    {
      "domain": "com.hk",
      "reason": "network_issue",
      "detail": "fetch_failed:HTTPSConnectionPool(host='com.hk', port=443): Max retries exceeded with url: / (Caused by NameResolutionError(\"HTTPSConnection(host='com.hk', port=443): Failed to resolve 'com.hk' ([Errno -5] No address associated with hostname)\"))",
      "matched_kw": ""
    },
    {
      "domain": "orangenews.hk",
      "reason": "content_blocked",
      "detail": "",
      "matched_kw": "政府"
    },
    {
      "domain": "wenweipo.com",
      "reason": "content_blocked",
      "detail": "",
      "matched_kw": "教育"
    },
    {
      "domain": "gamersky.com",
      "reason": "no_indicators",
      "detail": "",
      "matched_kw": ""
    },
    {
      "domain": "mpweekly.com",
      "reason": "network_issue",
      "detail": "fetch_failed:HTTPSConnectionPool(host='mpweekly.com', port=443): Max retries exceeded with url: / (Caused by SSLError(SSLError(1, '[SSL: TLSV1_UNRECOGNIZED_NAME] tlsv1 unrecognized name (_ssl.c:1016)')))",
      "matched_kw": ""
    },
    {
      "domain": "chunghwabookstore.com",
      "reason": "network_issue",
      "detail": "fetch_failed:HTTPSConnectionPool(host='chunghwabookstore.com', port=443): Max retries exceeded with url: / (Caused by SSLError(SSLCertVerificationError(1, '[SSL: CERTIFICATE_VERIFY_FAILED] certificate verify failed: self-signed certificate (_ssl.c:1016)')))",
      "matched_kw": ""
    },
    {
      "domain": "arlevard.com",
      "reason": "no_indicators",
      "detail": "",
      "matched_kw": ""
    },
    {
      "domain": "klook.com",
      "reason": "network_issue",
      "detail": "http_403",
      "matched_kw": ""
    },
    {
      "domain": "hkmemory.hk",
      "reason": "network_issue",
      "detail": "fetch_failed:HTTPSConnectionPool(host='hkmemory.hk', port=443): Max retries exceeded with url: / (Caused by SSLError(SSLCertVerificationError(1, \"[SSL: CERTIFICATE_VERIFY_FAILED] certificate verify failed: Hostname mismatch, certificate is not valid for 'hkmemory.hk'. (_ssl.c:1016)\")))",
      "matched_kw": ""
    },
    {
      "domain": "beinghongkong.com",
      "reason": "network_issue",
      "detail": "fetch_failed:HTTPSConnectionPool(host='beinghongkong.com', port=443): Max retries exceeded with url: / (Caused by SSLError(SSLError(1, '[SSL: SSLV3_ALERT_HANDSHAKE_FAILURE] sslv3 alert handshake failure (_ssl.c:1016)')))",
      "matched_kw": ""
    },
    {
      "domain": "shoplineapp.com",
      "reason": "no_indicators",
      "detail": "",
      "matched_kw": ""
    },
    {
      "domain": "m21.hk",
      "reason": "content_blocked",
      "detail": "",
      "matched_kw": "教育"
    },
    {
      "domain": "hkdance.com",
      "reason": "network_issue",
      "detail": "fetch_failed:HTTPSConnectionPool(host='hkdance.com', port=443): Max retries exceeded with url: / (Caused by SSLError(SSLCertVerificationError(1, \"[SSL: CERTIFICATE_VERIFY_FAILED] certificate verify failed: Hostname mismatch, certificate is not valid for 'hkdance.com'. (_ssl.c:1016)\")))",
      "matched_kw": ""
    },
    {
      "domain": "hkcna.hk",
      "reason": "content_blocked",
      "detail": "",
      "matched_kw": "政府"
    },
    {
      "domain": "tkww.hk",
      "reason": "content_blocked",
      "detail": "",
      "matched_kw": "直播"
    },
    {
      "domain": "gznf.net",
      "reason": "content_blocked",
      "detail": "",
      "matched_kw": "购物"
    },
    {
      "domain": "hkwl.org",
      "reason": "content_blocked",
      "detail": "",
      "matched_kw": "基金"
    },
    {
      "domain": "artandpiece.com",
      "reason": "no_indicators",
      "detail": "",
      "matched_kw": ""
    },
    {
      "domain": "mingpao.com",
      "reason": "network_issue",
      "detail": "http_403",
      "matched_kw": ""
    },
    {
      "domain": "gob.mx",
      "reason": "network_issue",
      "detail": "fetch_failed:HTTPSConnectionPool(host='gob.mx', port=443): Max retries exceeded with url: / (Caused by SSLError(SSLCertVerificationError(1, '[SSL: CERTIFICATE_VERIFY_FAILED] certificate verify failed: unable to get local issuer certificate (_ssl.c:1016)')))",
      "matched_kw": ""
    },
    {
      "domain": "tcb.tw",
      "reason": "content_blocked",
      "detail": "",
      "matched_kw": "法律"
    },
    {
      "domain": "threads.com",
      "reason": "no_indicators",
      "detail": "",
      "matched_kw": ""
    },
    {
      "domain": "ocacnews.net",
      "reason": "content_blocked",
      "detail": "",
      "matched_kw": "政府"
    },
    {
      "domain": "plurk.com",
      "reason": "no_indicators",
      "detail": "",
      "matched_kw": ""
    },
    {
      "domain": "udn.com",
      "reason": "no_indicators",
      "detail": "",
      "matched_kw": ""
    },
    {
      "domain": "sounova.com",
      "reason": "network_issue",
      "detail": "http_503",
      "matched_kw": ""
    },
    {
      "domain": "thinkingtaiwan.net",
      "reason": "network_issue",
      "detail": "fetch_failed:HTTPSConnectionPool(host='thinkingtaiwan.net', port=443): Max retries exceeded with url: / (Caused by SSLError(SSLCertVerificationError(1, \"[SSL: CERTIFICATE_VERIFY_FAILED] certificate verify failed: Hostname mismatch, certificate is not valid for 'thinkingtaiwan.net'. (_ssl.c:1016)\")))",
      "matched_kw": ""
    },
    {
      "domain": "taiwanngo.tw",
      "reason": "content_blocked",
      "detail": "",
      "matched_kw": "政府"
    },
    {
      "domain": "umeadow.com",
      "reason": "no_indicators",
      "detail": "",
      "matched_kw": ""
    },
    {
      "domain": "mirrormedia.mg",
      "reason": "no_indicators",
      "detail": "",
      "matched_kw": ""
    },
    {
      "domain": "culture.tw",
      "reason": "network_issue",
      "detail": "fetch_failed:HTTPSConnectionPool(host='culture.tw', port=443): Max retries exceeded with url: / (Caused by NameResolutionError(\"HTTPSConnection(host='culture.tw', port=443): Failed to resolve 'culture.tw' ([Errno -5] No address associated with hostname)\"))",
      "matched_kw": ""
    },
    {
      "domain": "locuspublishing.com",
      "reason": "network_issue",
      "detail": "fetch_failed:HTTPSConnectionPool(host='locuspublishing.com', port=443): Max retries exceeded with url: / (Caused by SSLError(SSLCertVerificationError(1, \"[SSL: CERTIFICATE_VERIFY_FAILED] certificate verify failed: Hostname mismatch, certificate is not valid for 'locuspublishing.com'. (_ssl.c:1016)\")))",
      "matched_kw": ""
    },
    {
      "domain": "autozone.com",
      "reason": "network_issue",
      "detail": "http_403",
      "matched_kw": ""
    },
    {
      "domain": "chamberofcommerce.com",
      "reason": "no_indicators",
      "detail": "",
      "matched_kw": ""
    },
    {
      "domain": "storeopeninghours.com",
      "reason": "no_indicators",
      "detail": "",
      "matched_kw": ""
    },
    {
      "domain": "us.com",
      "reason": "no_indicators",
      "detail": "",
      "matched_kw": ""
    },
    {
      "domain": "mystore411.com",
      "reason": "network_issue",
      "detail": "fetch_failed:HTTPSConnectionPool(host='mystore411.com', port=443): Max retries exceeded with url: / (Caused by SSLError(SSLCertVerificationError(1, '[SSL: CERTIFICATE_VERIFY_FAILED] certificate verify failed: unable to get local issuer certificate (_ssl.c:1016)')))",
      "matched_kw": ""
    },
    {
      "domain": "find-open.com",
      "reason": "network_issue",
      "detail": "http_403",
      "matched_kw": ""
    },
    {
      "domain": "anifun.cn",
      "reason": "content_blocked",
      "detail": "",
      "matched_kw": "直播"
    },
    {
      "domain": "yinghuaanime.com",
      "reason": "content_blocked",
      "detail": "",
      "matched_kw": "电影"
    },
    {
      "domain": "anibase.net",
      "reason": "content_blocked",
      "detail": "",
      "matched_kw": "体育"
    },
    {
      "domain": "xiehuio.com",
      "reason": "content_blocked",
      "detail": "",
      "matched_kw": "电影"
    },
    {
      "domain": "ofiii.com",
      "reason": "content_blocked",
      "detail": "",
      "matched_kw": "直播"
    },
    {
      "domain": "d-dmm.com",
      "reason": "content_blocked",
      "detail": "",
      "matched_kw": "金融"
    },
    {
      "domain": "weimh.com",
      "reason": "content_blocked",
      "detail": "",
      "matched_kw": "体育"
    },
    {
      "domain": "kalamanhua.com",
      "reason": "content_blocked",
      "detail": "",
      "matched_kw": "金融"
    },
    {
      "domain": "manhuatuan.com",
      "reason": "content_blocked",
      "detail": "",
      "matched_kw": "金融"
    },
    {
      "domain": "roumanhua.net",
      "reason": "network_issue",
      "detail": "http_403",
      "matched_kw": ""
    },
    {
      "domain": "microsoft.com",
      "reason": "no_indicators",
      "detail": "",
      "matched_kw": ""
    },
    {
      "domain": "office.com",
      "reason": "content_blocked",
      "detail": "",
      "matched_kw": "教育"
    },
    {
      "domain": "live.com",
      "reason": "no_indicators",
      "detail": "",
      "matched_kw": ""
    },
    {
      "domain": "outlook.com",
      "reason": "no_indicators",
      "detail": "",
      "matched_kw": ""
    },
    {
      "domain": "xbox.com",
      "reason": "no_indicators",
      "detail": "",
      "matched_kw": ""
    },
    {
      "domain": "linkedin.com",
      "reason": "content_blocked",
      "detail": "",
      "matched_kw": "医疗"
    },
    {
      "domain": "ferreteriasuy.com",
      "reason": "no_indicators",
      "detail": "",
      "matched_kw": ""
    },
    {
      "domain": "com.uy",
      "reason": "network_issue",
      "detail": "fetch_failed:HTTPSConnectionPool(host='com.uy', port=443): Max retries exceeded with url: / (Caused by NameResolutionError(\"HTTPSConnection(host='com.uy', port=443): Failed to resolve 'com.uy' ([Errno -5] No address associated with hostname)\"))",
      "matched_kw": ""
    },
    {
      "domain": "cybo.com",
      "reason": "network_issue",
      "detail": "http_403",
      "matched_kw": ""
    },
    {
      "domain": "dirijasehistorial.com",
      "reason": "network_issue",
      "detail": "http_403",
      "matched_kw": ""
    },
    {
      "domain": "infobel.com",
      "reason": "network_issue",
      "detail": "http_403",
      "matched_kw": ""
    },
    {
      "domain": "mvdgestiona.uy",
      "reason": "no_indicators",
      "detail": "",
      "matched_kw": ""
    },
    {
      "domain": "uruguaypymes.com",
      "reason": "no_indicators",
      "detail": "",
      "matched_kw": ""
    },
    {
      "domain": "kleox99.github.io",
      "reason": "network_issue",
      "detail": "http_404",
      "matched_kw": ""
    },
    {
      "domain": "mapquest.com",
      "reason": "no_indicators",
      "detail": "",
      "matched_kw": ""
    },
    {
      "domain": "novacircle.com",
      "reason": "no_indicators",
      "detail": "",
      "matched_kw": ""
    },
    {
      "domain": "storebranch.com",
      "reason": "no_indicators",
      "detail": "",
      "matched_kw": ""
    },
    {
      "domain": "thew1london.com",
      "reason": "no_indicators",
      "detail": "",
      "matched_kw": ""
    },
    {
      "domain": "merriam-webster.com",
      "reason": "network_issue",
      "detail": "http_403",
      "matched_kw": ""
    },
    {
      "domain": "cambridge.org",
      "reason": "network_issue",
      "detail": "http_403",
      "matched_kw": ""
    },
    {
      "domain": "dictionary.com",
      "reason": "no_indicators",
      "detail": "",
      "matched_kw": ""
    },
    {
      "domain": "thefreedictionary.com",
      "reason": "network_issue",
      "detail": "http_403",
      "matched_kw": ""
    },
    {
      "domain": "britannica.com",
      "reason": "network_issue",
      "detail": "http_403",
      "matched_kw": ""
    },
    {
      "domain": "civiltutorials.com",
      "reason": "no_indicators",
      "detail": "",
      "matched_kw": ""
    },
    {
      "domain": "usdictionary.com",
      "reason": "no_indicators",
      "detail": "",
      "matched_kw": ""
    },
    {
      "domain": "collinsdictionary.com",
      "reason": "network_issue",
      "detail": "http_403",
      "matched_kw": ""
    },
    {
      "domain": "aihr.com",
      "reason": "no_indicators",
      "detail": "",
      "matched_kw": ""
    },
    {
      "domain": "smallbiztrends.com",
      "reason": "no_indicators",
      "detail": "",
      "matched_kw": ""
    },
    {
      "domain": "ijfans.org",
      "reason": "no_indicators",
      "detail": "",
      "matched_kw": ""
    },
    {
      "domain": "sustainability-directory.com",
      "reason": "no_indicators",
      "detail": "",
      "matched_kw": ""
    },
    {
      "domain": "matterapp.com",
      "reason": "no_indicators",
      "detail": "",
      "matched_kw": ""
    },
    {
      "domain": "surveymonkey.com",
      "reason": "no_indicators",
      "detail": "",
      "matched_kw": ""
    },
    {
      "domain": "wrenly.ai",
      "reason": "no_indicators",
      "detail": "",
      "matched_kw": ""
    },
    {
      "domain": "valamis.com",
      "reason": "no_indicators",
      "detail": "",
      "matched_kw": ""
    },
    {
      "domain": "mihcm.com",
      "reason": "no_indicators",
      "detail": "",
      "matched_kw": ""
    },
    {
      "domain": "fredericwi.com",
      "reason": "no_indicators",
      "detail": "",
      "matched_kw": ""
    },
    {
      "domain": "thisbigwildworld.com",
      "reason": "no_indicators",
      "detail": "",
      "matched_kw": ""
    },
    {
      "domain": "zillow.com",
      "reason": "no_indicators",
      "detail": "",
      "matched_kw": ""
    },
    {
      "domain": "getskyscraper.com",
      "reason": "no_indicators",
      "detail": "",
      "matched_kw": ""
    },
    {
      "domain": "getbluepilot.com",
      "reason": "no_indicators",
      "detail": "",
      "matched_kw": ""
    },
    {
      "domain": "circleboom.com",
      "reason": "no_indicators",
      "detail": "",
      "matched_kw": ""
    },
    {
      "domain": "walls.io",
      "reason": "no_indicators",
      "detail": "",
      "matched_kw": ""
    },
    {
      "domain": "socialwalls.com",
      "reason": "network_issue",
      "detail": "http_403",
      "matched_kw": ""
    },
    {
      "domain": "bsky.app",
      "reason": "no_indicators",
      "detail": "",
      "matched_kw": ""
    },
    {
      "domain": "debbieohi.com",
      "reason": "no_indicators",
      "detail": "",
      "matched_kw": ""
    },
    {
      "domain": "bskyinfo.com",
      "reason": "no_indicators",
      "detail": "",
      "matched_kw": ""
    },
    {
      "domain": "whatsapp.com",
      "reason": "network_issue",
      "detail": "http_400",
      "matched_kw": ""
    },
    {
      "domain": "gosgc.com",
      "reason": "no_indicators",
      "detail": "",
      "matched_kw": ""
    },
    {
      "domain": "icy-veins.com",
      "reason": "no_indicators",
      "detail": "",
      "matched_kw": ""
    },
    {
      "domain": "wordsanswers.info",
      "reason": "no_indicators",
      "detail": "",
      "matched_kw": ""
    },
    {
      "domain": "verifiedcarrier.com",
      "reason": "no_indicators",
      "detail": "",
      "matched_kw": ""
    },
    {
      "domain": "verifycarrier.com",
      "reason": "no_indicators",
      "detail": "",
      "matched_kw": ""
    },
    {
      "domain": "travelers.com",
      "reason": "no_indicators",
      "detail": "",
      "matched_kw": ""
    },
    {
      "domain": "nmfta.org",
      "reason": "no_indicators",
      "detail": "",
      "matched_kw": ""
    },
    {
      "domain": "foreigh.com",
      "reason": "no_indicators",
      "detail": "",
      "matched_kw": ""
    },
    {
      "domain": "carriersource.io",
      "reason": "no_indicators",
      "detail": "",
      "matched_kw": ""
    },
    {
      "domain": "parliament.uk",
      "reason": "network_issue",
      "detail": "http_403",
      "matched_kw": ""
    },
    {
      "domain": "gov.uk",
      "reason": "no_indicators",
      "detail": "",
      "matched_kw": ""
    },
    {
      "domain": "parliamenttoday.com",
      "reason": "no_indicators",
      "detail": "",
      "matched_kw": ""
    },
    {
      "domain": "stackoverflow.com",
      "reason": "no_indicators",
      "detail": "",
      "matched_kw": ""
    },
    {
      "domain": "thegradcafe.com",
      "reason": "network_issue",
      "detail": "http_403",
      "matched_kw": ""
    },
    {
      "domain": "doc-openvideo.vercel.app",
      "reason": "content_blocked",
      "detail": "",
      "matched_kw": "直播"
    },
    {
      "domain": "bilibili-evolved-doc.vercel.app",
      "reason": "no_indicators",
      "detail": "",
      "matched_kw": ""
    },
    {
      "domain": "fvtt-cn.vercel.app",
      "reason": "content_blocked",
      "detail": "",
      "matched_kw": "软件"
    },
    {
      "domain": "moyud.vercel.app",
      "reason": "no_indicators",
      "detail": "",
      "matched_kw": ""
    },
    {
      "domain": "blog-ffzz.vercel.app",
      "reason": "content_blocked",
      "detail": "",
      "matched_kw": "导航"
    },
    {
      "domain": "pixiv-reader.vercel.app",
      "reason": "no_indicators",
      "detail": "",
      "matched_kw": ""
    },
    {
      "domain": "xiaotou.vercel.app",
      "reason": "no_indicators",
      "detail": "",
      "matched_kw": ""
    },
    {
      "domain": "theflix.vercel.app",
      "reason": "no_indicators",
      "detail": "",
      "matched_kw": ""
    },
    {
      "domain": "rule34dle.vercel.app",
      "reason": "no_indicators",
      "detail": "",
      "matched_kw": ""
    },
    {
      "domain": "xiangchuifeng-github-io.vercel.app",
      "reason": "content_blocked",
      "detail": "",
      "matched_kw": "汽车"
    },
    {
      "domain": "dongjian.vercel.app",
      "reason": "content_blocked",
      "detail": "",
      "matched_kw": "博客"
    },
    {
      "domain": "v2ex.vercel.app",
      "reason": "content_blocked",
      "detail": "",
      "matched_kw": "编程"
    },
    {
      "domain": "bcd-app.fly.dev",
      "reason": "no_indicators",
      "detail": "",
      "matched_kw": ""
    },
    {
      "domain": "cancheo-web.fly.dev",
      "reason": "network_issue",
      "detail": "fetch_failed:HTTPSConnectionPool(host='cancheo-web.fly.dev', port=443): Max retries exceeded with url: / (Caused by NameResolutionError(\"HTTPSConnection(host='cancheo-web.fly.dev', port=443): Failed to resolve 'cancheo-web.fly.dev' ([Errno -2] Name or service not known)\"))",
      "matched_kw": ""
    },
    {
      "domain": "references.fly.dev",
      "reason": "no_indicators",
      "detail": "",
      "matched_kw": ""
    },
    {
      "domain": "wooky.fly.dev",
      "reason": "no_indicators",
      "detail": "",
      "matched_kw": ""
    },
    {
      "domain": "fly-changelog.fly.dev",
      "reason": "no_indicators",
      "detail": "",
      "matched_kw": ""
    },
    {
      "domain": "zamgot-studio-dev.fly.dev",
      "reason": "anti_pattern",
      "detail": "",
      "matched_kw": "18+"
    },
    {
      "domain": "wooey.fly.dev",
      "reason": "content_blocked",
      "detail": "",
      "matched_kw": "导航"
    },
    {
      "domain": "zamgot-dev.fly.dev",
      "reason": "anti_pattern",
      "detail": "",
      "matched_kw": "18+"
    },
    {
      "domain": "mythwright.fly.dev",
      "reason": "no_indicators",
      "detail": "",
      "matched_kw": ""
    },
    {
      "domain": "flyio-landing.fly.dev",
      "reason": "no_indicators",
      "detail": "",
      "matched_kw": ""
    },
    {
      "domain": "authgo.fly.dev",
      "reason": "no_indicators",
      "detail": "",
      "matched_kw": ""
    },
    {
      "domain": "romparty.fly.dev",
      "reason": "no_indicators",
      "detail": "",
      "matched_kw": ""
    },
    {
      "domain": "cltapp.fly.dev",
      "reason": "no_indicators",
      "detail": "",
      "matched_kw": ""
    },
    {
      "domain": "devault-app.fly.dev",
      "reason": "no_indicators",
      "detail": "",
      "matched_kw": ""
    },
    {
      "domain": "get-newfolders-here.fly.dev",
      "reason": "network_issue",
      "detail": "fetch_failed:HTTPSConnectionPool(host='get-newfolders-here.fly.dev', port=443): Max retries exceeded with url: / (Caused by NameResolutionError(\"HTTPSConnection(host='get-newfolders-here.fly.dev', port=443): Failed to resolve 'get-newfolders-here.fly.dev' ([Errno -2] Name or service not known)\"))",
      "matched_kw": ""
    },
    {
      "domain": "studiom.fly.dev",
      "reason": "no_indicators",
      "detail": "",
      "matched_kw": ""
    },
    {
      "domain": "tohray.fly.dev",
      "reason": "no_indicators",
      "detail": "",
      "matched_kw": ""
    },
    {
      "domain": "nthulabook.onrender.com",
      "reason": "content_blocked",
      "detail": "",
      "matched_kw": "政府"
    },
    {
      "domain": "seer-calculator.onrender.com",
      "reason": "no_indicators",
      "detail": "",
      "matched_kw": ""
    },
    {
      "domain": "node-snapdrop.onrender.com",
      "reason": "no_indicators",
      "detail": "",
      "matched_kw": ""
    },
    {
      "domain": "unblockthetruth.onrender.com",
      "reason": "content_blocked",
      "detail": "",
      "matched_kw": "导航"
    },
    {
      "domain": "dmo-market.onrender.com",
      "reason": "no_indicators",
      "detail": "",
      "matched_kw": ""
    },
    {
      "domain": "addon-marvel.onrender.com",
      "reason": "no_indicators",
      "detail": "",
      "matched_kw": ""
    },
    {
      "domain": "d3aoa10o0410wd.cloudfront.net",
      "reason": "content_blocked",
      "detail": "",
      "matched_kw": "体育"
    },
    {
      "domain": "dnjtwtgi48217.cloudfront.net",
      "reason": "anti_pattern",
      "detail": "",
      "matched_kw": "成人"
    },
    {
      "domain": "d1hl9setcycg81.cloudfront.net",
      "reason": "anti_pattern",
      "detail": "",
      "matched_kw": "成人"
    },
    {
      "domain": "d6lvl8l2l26yp.cloudfront.net",
      "reason": "content_blocked",
      "detail": "",
      "matched_kw": "体育"
    },
    {
      "domain": "d31a8rdj19i5e2.cloudfront.net",
      "reason": "content_blocked",
      "detail": "",
      "matched_kw": "体育"
    },
    {
      "domain": "d1s8wm47asyysy.cloudfront.net",
      "reason": "no_indicators",
      "detail": "",
      "matched_kw": ""
    },
    {
      "domain": "d1na3f9tshcp4p.cloudfront.net",
      "reason": "anti_pattern",
      "detail": "",
      "matched_kw": "成人"
    },
    {
      "domain": "dpz3pzoteix4e.cloudfront.net",
      "reason": "content_blocked",
      "detail": "",
      "matched_kw": "直播"
    },
    {
      "domain": "discsmijr8t6l.cloudfront.net",
      "reason": "content_blocked",
      "detail": "",
      "matched_kw": "体育"
    },
    {
      "domain": "d3ra9nqn08kl2e.cloudfront.net",
      "reason": "anti_pattern",
      "detail": "",
      "matched_kw": "成人"
    },
    {
      "domain": "docs.replit.com",
      "reason": "anti_pattern",
      "detail": "",
      "matched_kw": "18r"
    },
    {
      "domain": "learn.replit.com",
      "reason": "no_indicators",
      "detail": "",
      "matched_kw": ""
    },
    {
      "domain": "replit.com",
      "reason": "no_indicators",
      "detail": "",
      "matched_kw": ""
    },
    {
      "domain": "status.replit.com",
      "reason": "network_issue",
      "detail": "http_403",
      "matched_kw": ""
    },
    {
      "domain": "links.replit.com",
      "reason": "no_indicators",
      "detail": "",
      "matched_kw": ""
    },
    {
      "domain": "blog.replit.com",
      "reason": "no_indicators",
      "detail": "",
      "matched_kw": ""
    },
    {
      "domain": "czn-save-cal.web.app",
      "reason": "no_indicators",
      "detail": "",
      "matched_kw": ""
    },
    {
      "domain": "fatimae-and-louie.web.app",
      "reason": "no_indicators",
      "detail": "",
      "matched_kw": ""
    },
    {
      "domain": "baton-app-ea7b5.web.app",
      "reason": "no_indicators",
      "detail": "",
      "matched_kw": ""
    },
    {
      "domain": "sodehiku.web.app",
      "reason": "no_indicators",
      "detail": "",
      "matched_kw": ""
    },
    {
      "domain": "gazoaetns.onrender.com",
      "reason": "network_issue",
      "detail": "http_404",
      "matched_kw": ""
    },
    {
      "domain": "cinebai.onrender.com",
      "reason": "no_indicators",
      "detail": "",
      "matched_kw": ""
    },
    {
      "domain": "comedy-mastermind.onrender.com",
      "reason": "no_indicators",
      "detail": "",
      "matched_kw": ""
    },
    {
      "domain": "ts4rebels-info-page.onrender.com",
      "reason": "no_indicators",
      "detail": "",
      "matched_kw": ""
    },
    {
      "domain": "aopg-calculator.onrender.com",
      "reason": "no_indicators",
      "detail": "",
      "matched_kw": ""
    },
    {
      "domain": "techvyro-movies.onrender.com",
      "reason": "no_indicators",
      "detail": "",
      "matched_kw": ""
    },
    {
      "domain": "zzz-run-archive.onrender.com",
      "reason": "no_indicators",
      "detail": "",
      "matched_kw": ""
    },
    {
      "domain": "bungatiga.onrender.com",
      "reason": "anti_pattern",
      "detail": "",
      "matched_kw": "18+"
    },
    {
      "domain": "autostreamtest.onrender.com",
      "reason": "no_indicators",
      "detail": "",
      "matched_kw": ""
    },
    {
      "domain": "fmf-internal-app.onrender.com",
      "reason": "no_indicators",
      "detail": "",
      "matched_kw": ""
    },
    {
      "domain": "irothordertracker-4.onrender.com",
      "reason": "no_indicators",
      "detail": "",
      "matched_kw": ""
    },
    {
      "domain": "pattern-playground.onrender.com",
      "reason": "no_indicators",
      "detail": "",
      "matched_kw": ""
    },
    {
      "domain": "unmiraclepourlafrance.onrender.com",
      "reason": "no_indicators",
      "detail": "",
      "matched_kw": ""
    },
    {
      "domain": "qianchuan.onrender.com",
      "reason": "content_blocked",
      "detail": "",
      "matched_kw": "导航"
    },
    {
      "domain": "axutongxue.onrender.com",
      "reason": "content_blocked",
      "detail": "",
      "matched_kw": "编程"
    },
    {
      "domain": "reseau-fouineurs.onrender.com",
      "reason": "no_indicators",
      "detail": "",
      "matched_kw": ""
    },
    {
      "domain": "mangogo.pages.dev",
      "reason": "no_indicators",
      "detail": "",
      "matched_kw": ""
    },
    {
      "domain": "miyomi.pages.dev",
      "reason": "no_indicators",
      "detail": "",
      "matched_kw": ""
    },
    {
      "domain": "playtorrio.pages.dev",
      "reason": "no_indicators",
      "detail": "",
      "matched_kw": ""
    },
    {
      "domain": "sadg166.pages.dev",
      "reason": "content_blocked",
      "detail": "",
      "matched_kw": "导航"
    },
    {
      "domain": "anibrain-closure.pages.dev",
      "reason": "no_indicators",
      "detail": "",
      "matched_kw": ""
    },
    {
      "domain": "landing-futon.pages.dev",
      "reason": "no_indicators",
      "detail": "",
      "matched_kw": ""
    },
    {
      "domain": "olympus.pages.dev",
      "reason": "no_indicators",
      "detail": "",
      "matched_kw": ""
    },
    {
      "domain": "th3-anime.pages.dev",
      "reason": "no_indicators",
      "detail": "",
      "matched_kw": ""
    },
    {
      "domain": "manga-go.pages.dev",
      "reason": "no_indicators",
      "detail": "",
      "matched_kw": ""
    },
    {
      "domain": "futonapp.pages.dev",
      "reason": "no_indicators",
      "detail": "",
      "matched_kw": ""
    },
    {
      "domain": "icctutorial.pages.dev",
      "reason": "no_indicators",
      "detail": "",
      "matched_kw": ""
    },
    {
      "domain": "batomirrors.pages.dev",
      "reason": "network_issue",
      "detail": "fetch_failed:HTTPSConnectionPool(host='batomirrors.pages.dev', port=443): Max retries exceeded with url: / (Caused by NameResolutionError(\"HTTPSConnection(host='batomirrors.pages.dev', port=443): Failed to resolve 'batomirrors.pages.dev' ([Errno -2] Name or service not known)\"))",
      "matched_kw": ""
    },
    {
      "domain": "heartivetv.pages.dev",
      "reason": "no_indicators",
      "detail": "",
      "matched_kw": ""
    },
    {
      "domain": "miguapp.pages.dev",
      "reason": "no_indicators",
      "detail": "",
      "matched_kw": ""
    }
  ],
  "matchedByKeyword": {
    "漫": [
      "51manga.com",
      "ai-manga-generator.vercel.app",
      "anibk.com",
      "anime-gensaku-guide.onrender.com",
      "bomtoon.tw",
      "bookmanta.com",
      "comic-ogyaaa.com",
      "comic-walker.com",
      "comicbunch-kai.com",
      "corocoro.jp",
      "creative-comic.tw",
      "dm5.com",
      "dokumanhk.net",
      "exview.vercel.app",
      "fleur-collections.com",
      "gugu3.com",
      "hemh.cc",
      "hp-gamma-eight.vercel.app",
      "jump-mangasho.com",
      "manga-mee.jp",
      "manga-shinchan.com",
      "mangashare.vercel.app",
      "manhuaren.com",
      "mechacomic.jp",
      "mojoin.com",
      "mycomic.com",
      "nickstember.com",
      "piccoma.com",
      "pixiv-viewer.vercel.app",
      "quire-comic.com",
      "rit.vercel.app",
      "sg.vercel.app",
      "shonenmagazine.com",
      "to-corona-ex.com",
      "toptoon.net"
    ]
  }
}